CHANGES.txt
COPYRIGHT.txt
LICENSE.txt
bootstrap.py
buildout.cfg
setup.py
src/hurry/__init__.py
src/hurry.zoperesource.egg-info/PKG-INFO
src/hurry.zoperesource.egg-info/SOURCES.txt
src/hurry.zoperesource.egg-info/dependency_links.txt
src/hurry.zoperesource.egg-info/namespace_packages.txt
src/hurry.zoperesource.egg-info/not-zip-safe
src/hurry.zoperesource.egg-info/requires.txt
src/hurry.zoperesource.egg-info/top_level.txt
src/hurry/zoperesource/README.txt
src/hurry/zoperesource/__init__.py
src/hurry/zoperesource/configure.zcml
src/hurry/zoperesource/meta.zcml
src/hurry/zoperesource/zcml.py
src/hurry/zoperesource/zopesupport.py
src/hurry/zoperesource/tests/__init__.py
src/hurry/zoperesource/tests/ftesting.zcml
src/hurry/zoperesource/tests/test_bottom.pt
src/hurry/zoperesource/tests/test_multiple.pt
src/hurry/zoperesource/tests/test_single.pt
src/hurry/zoperesource/tests/tests.py
src/hurry/zoperesource/tests/view.py