Metadata-Version: 1.0
Name: hurry.zoperesource
Version: 0.6
Summary: hurry.resource integration for Zope.
Home-page: http://pypi.python.org/pypi/hurry.zoperesource
Author: Martijn Faassen
Author-email: faassen@startifact.com
License: ZPL
Platform: UNKNOWN
Classifier: Framework :: Zope3
